jupyterlab_rubinhub/__init__.py
jupyterlab_rubinhub/__init__.pyc
jupyterlab_rubinhub/handlers.py
jupyterlab_rubinhub/handlers.pyc
jupyterlab_rubinhub-0.0.1.dist-info/LICENSE
jupyterlab_rubinhub-0.0.1.dist-info/METADATA
jupyterlab_rubinhub-0.0.1.dist-info/WHEEL
jupyterlab_rubinhub-0.0.1.dist-info/top_level.txt
jupyterlab_rubinhub-0.0.1.dist-info/RECORD
